[
  {
    "slug": "social-media-marketing",
    "title": "Social Media Marketing",
    "shortTitle": "Social Media\nMarketing",
    "index": 1,
    "image": "../../assets/pics/card-pic3.png",
    "color": "green",
    "description": "Build a loyal community and amplify your brand voice across social platforms. From content calendars to engagement strategies, we turn followers into customers.",
    "features": ["Content Strategy", "Community Management", "Paid Social", "Analytics"],
    "details": [
      "Platform-specific strategy for Instagram, LinkedIn, TikTok, and more",
      "Content calendar creation and scheduling",
      "Community management and engagement",
      "Paid social advertising with audience targeting",
      "Performance analytics and monthly reporting"
    ],
    "heroText": "Grow your brand presence and engage your audience where they spend their time."
  }
]
